pypi_project/__init__.py
pypi_project/config.py
pypi_project/main.py
pypi_shell-0.1.2.dist-info/LICENSE
pypi_shell-0.1.2.dist-info/METADATA
pypi_shell-0.1.2.dist-info/WHEEL
pypi_shell-0.1.2.dist-info/entry_points.txt
pypi_shell-0.1.2.dist-info/top_level.txt
pypi_shell-0.1.2.dist-info/RECORD
