Metadata-Version: 2.1
Name: pypi-shell
Version: 0.1.2
Summary: description
Home-page: https://github.com/WuKunhuan163/PyPI-Project
Author: wukunhuan
Author-email: wukunhuan1208@163.com
Project-URL: Source, https://github.com/WuKunhuan163/PyPI-Project
Classifier: Programming Language :: Python :: 3
Classifier: License :: OSI Approved :: MIT License
Classifier: Operating System :: OS Independent
Requires-Python: >=3
License-File: LICENSE
